Workbook

Sheet Summary
B1: Order-to-Cash Performance - Olist E-commerce
B2: Where is the business losing revenue or customer satisfaction? Sep-2016 to Oct-2018, real Olist data. Amounts in R$.
B4: TOTAL REVENUE (R$) | D4: ORDERS | F4: AVG ORDER VALUE (R$) | H4: ON-TIME DELIVERY % | J4: AVG REVIEW SCORE (1-5)
B5: Item prices, excl. freight | D5: Not canceled / unavailable | F5: Revenue / orders | H5: Delivered on or before promised day | J5: Latest review per order
B6: =SUM(Monthly!C4:C27) -> 13494401 | D6: =SUM(Monthly!B4:B27) -> 98199 | F6: =B6/D6 -> 137.41892 | H6: =1-State_Delivery!C31/State_Delivery!B31 -> 0.9322691 | J6: =Review_Scores!B11 -> 4.0863863
B8: HOW TO READ THIS
B9: 1) The five cards at the top are the headline numbers; they are calculated by formulas from the data tabs. 2) Revenue chart: is the business growing? Category chart: which product groups earn the money? State chart: the taller the bar, the larger the share of orders that arrive after the promised date. Bottom-right chart: how much a late delivery hurts the customer review score. 3) "Late" means delivered on a later day than the estimated delivery date. The tabs Monthly, Categories, State_Delivery, Review_Impact and Notes hold the data and definitions.
G48: KEY TAKEAWAYS (calculated)
G49: ="On-time orders average "&TEXT(Review_Impact!C4,"0.00")&" stars." -> On-time orders average 4.29 stars.
G51: ="Orders more than 7 days late average "&TEXT(Review_Impact!C7,"0.00")&" stars." -> Orders more than 7 days late average 1.70 stars.
G53: ="Late orders are "&TEXT(Review_Impact!C10,"0.0%")&" of reviewed orders." -> Late orders are 6.7% of reviewed orders.
G55: ="Worst state for lateness: "&INDEX(State_Delivery!A4:A30,MATCH(MAX(State_Delivery!D4:D30),State_Delivery!D4:D30,0))&" ("&TEXT(MAX(State_Delivery!D4:D30),"0.0%")&" late)." -> Worst state for lateness: AL (21.4% late).
G57: ="Top 10 categories = "&TEXT(Categories!F14,"0.0%")&" of revenue." -> Top 10 categories = 62.4% of revenue.

Sheet Monthly
A1: Monthly revenue and orders (orders not canceled/unavailable) - values from SQL Q1; blue = values from SQL, black = formulas
A3: Order month | B3: Orders | C3: Revenue (R$) | D3: Avg order value (R$) | E3: Revenue vs prior month
A4: 2016-09 | B4: 2 | C4: 207.86 | D4: =C4/B4 -> 103.93 | E4: n/a
A5: 2016-10 | B5: 290 | C5: 44507.3 | D5: =C5/B5 -> 153.47345 | E5: =IF(B4>=100,C5/C4-1,"n/a") -> n/a
A6: 2016-12 | B6: 1 | C6: 10.9 | D6: =C6/B6 -> 10.9 | E6: =IF(B5>=100,C6/C5-1,"n/a") -> -0.9997551
A7: 2017-01 | B7: 787 | C7: 120098.27 | D7: =C7/B7 -> 152.60263 | E7: =IF(B6>=100,C7/C6-1,"n/a") -> n/a
A8: 2017-02 | B8: 1718 | C8: 244959.35 | D8: =C8/B8 -> 142.58402 | E8: =IF(B7>=100,C8/C7-1,"n/a") -> 1.0396576
A9: 2017-03 | B9: 2617 | C9: 368341.32 | D9: =C9/B9 -> 140.74945 | E9: =IF(B8>=100,C9/C8-1,"n/a") -> 0.50368345
A10: 2017-04 | B10: 2377 | C10: 353842.98 | D10: =C10/B10 -> 148.86116 | E10: =IF(B9>=100,C10/C9-1,"n/a") -> -0.039361156
A11: 2017-05 | B11: 3640 | C11: 503159.19 | D11: =C11/B11 -> 138.23055 | E11: =IF(B10>=100,C11/C10-1,"n/a") -> 0.42198438
A12: 2017-06 | B12: 3205 | C12: 429916.61 | D12: =C12/B12 -> 134.13935 | E12: =IF(B11>=100,C12/C11-1,"n/a") -> -0.14556542
A13: 2017-07 | B13: 3946 | C13: 492287.3 | D13: =C13/B13 -> 124.75603 | E13: =IF(B12>=100,C13/C12-1,"n/a") -> 0.14507625
A14: 2017-08 | B14: 4272 | C14: 568245.79 | D14: =C14/B14 -> 133.01634 | E14: =IF(B13>=100,C14/C13-1,"n/a") -> 0.15429707
A15: 2017-09 | B15: 4227 | C15: 621415.91 | D15: =C15/B15 -> 147.0111 | E15: =IF(B14>=100,C15/C14-1,"n/a") -> 0.093568876
A16: 2017-10 | B16: 4547 | C16: 660179.62 | D16: =C16/B16 -> 145.19015 | E16: =IF(B15>=100,C16/C15-1,"n/a") -> 0.062379655
... A27: 2018-09 | B27: 1 | C27: 145 | D27: =C27/B27 -> 145 | E27: =IF(B26>=100,C27/C26-1,"n/a") -> -0.99982918
A28: Total | B28: =SUM(B4:B27) -> 98199 | C28: =SUM(C4:C27) -> 13494401 | D28: =C28/B28 -> 137.41892
A30: Note: 2016 months and Sep-2018 have only a handful of orders, so the trend chart on the Summary uses Jan-2017 to Aug-2018 only. Totals include every month.

Sheet Categories
A1: Top 10 product categories by revenue - values from SQL Q2
A3: Rank | B3: Category | C3: Orders | D3: Items sold | E3: Revenue (R$) | F3: Share of total revenue
A4: 1 | B4: health_beauty | C4: 8800 | D4: 9634 | E4: 1255695.1 | F4: =E4/Summary!$B$6 -> 0.093053049
A5: 2 | B5: watches_gifts | C5: 5604 | D5: 5970 | E5: 1198185.2 | F5: =E5/Summary!$B$6 -> 0.088791287
A6: 3 | B6: bed_bath_table | C6: 9399 | D6: 11097 | E6: 1035964.1 | F6: =E6/Summary!$B$6 -> 0.07676992
A7: 4 | B7: sports_leisure | C7: 7673 | D7: 8590 | E7: 979740.92 | F7: =E7/Summary!$B$6 -> 0.072603515
A8: 5 | B8: computers_accessories | C8: 6654 | D8: 7781 | E8: 904322.02 | F8: =E8/Summary!$B$6 -> 0.067014611
A9: 6 | B9: furniture_decor | C9: 6425 | D9: 8298 | E9: 727465.05 | F9: =E9/Summary!$B$6 -> 0.053908659
A10: 7 | B10: housewares | C10: 5847 | D10: 6915 | E10: 626825.8 | F10: =E10/Summary!$B$6 -> 0.046450807
A11: 8 | B11: cool_stuff | C11: 3616 | D11: 3779 | E11: 620770.49 | F11: =E11/Summary!$B$6 -> 0.046002079
A12: 9 | B12: auto | C12: 3872 | D12: 4204 | E12: 586585.73 | F12: =E12/Summary!$B$6 -> 0.043468824
A13: 10 | B13: garden_tools | C13: 3505 | D13: 4328 | E13: 481009.94 | F13: =E13/Summary!$B$6 -> 0.03564515
A14: Top 10 total | E14: =SUM(E4:E13) -> 8416564.3 | F14: =SUM(F4:F13) -> 0.6237079

Sheet State_Delivery
A1: Delivery performance by customer state (delivered orders) - values from SQL Q3 and Q4
A3: State | B3: Delivered orders | C3: Late orders | D3: Late % | E3: Avg actual days | F3: Avg promised days | G3: Days earlier than promised
A4: AL | B4: 397 | C4: 85 | D4: =C4/B4 -> 0.21410579 | E4: 24.5 | F4: 32.6 | G4: =F4-E4 -> 8.1
A5: MA | B5: 717 | C5: 125 | D5: =C5/B5 -> 0.17433752 | E5: 21.6 | F5: 30.5 | G5: =F5-E5 -> 8.9
A6: SE | B6: 335 | C6: 51 | D6: =C6/B6 -> 0.15223881 | E6: 21.5 | F6: 30.8 | G6: =F6-E6 -> 9.3
A7: PI | B7: 476 | C7: 66 | D7: =C7/B7 -> 0.13865546 | E7: 19.5 | F7: 30.1 | G7: =F7-E7 -> 10.6
A8: CE | B8: 1279 | C8: 176 | D8: =C8/B8 -> 0.13760751 | E8: 21.3 | F8: 31.4 | G8: =F8-E8 -> 10.1
A9: RR | B9: 41 | C9: 5 | D9: =C9/B9 -> 0.12195122 | E9: 29.4 | F9: 46 | G9: =F9-E9 -> 16.6
A10: BA | B10: 3256 | C10: 396 | D10: =C10/B10 -> 0.12162162 | E10: 19.3 | F10: 29.4 | G10: =F10-E10 -> 10.1
A11: RJ | B11: 12350 | C11: 1495 | D11: =C11/B11 -> 0.12105263 | E11: 15.3 | F11: 26.4 | G11: =F11-E11 -> 11.1
A12: PA | B12: 946 | C12: 106 | D12: =C12/B12 -> 0.11205074 | E12: 23.8 | F12: 37.2 | G12: =F12-E12 -> 13.4
A13: ES | B13: 1995 | C13: 214 | D13: =C13/B13 -> 0.10726817 | E13: 15.8 | F13: 25.6 | G13: =F13-E13 -> 9.8
A14: PB | B14: 517 | C14: 54 | D14: =C14/B14 -> 0.10444874 | E14: 20.4 | F14: 33 | G14: =F14-E14 -> 12.6
A15: TO | B15: 274 | C15: 27 | D15: =C15/B15 -> 0.098540146 | E15: 17.7 | F15: 29.1 | G15: =F15-E15 -> 11.4
... A30: AM | B30: 145 | C30: 4 | D30: =C30/B30 -> 0.027586207 | E30: 26.4 | F30: 45.3 | G30: =F30-E30 -> 18.9
A31: All states | B31: =SUM(B4:B30) -> 96470 | C31: =SUM(C4:C30) -> 6534 | D31: =C31/B31 -> 0.067730901
A33: Late = delivered on a later calendar day than the estimated delivery date. Sorted by late % (worst first). Small states (AP, RR, AC, AM, RO) have under 250 orders, so their % moves a lot.

Sheet Review_Impact
A1: Late delivery vs customer review score (delivered orders with a review) - values from SQL Q5
A3: Delivery outcome | B3: Reviewed orders | C3: Avg review score (1-5) | D3: % bad reviews (1-2 stars) | E3: % five-star
A4: On time or early | B4: 89443 | C4: 4.29 | D4: 0.093 | E4: 0.623
A5: Late 1-3 days | B5: 1852 | C5: 3.29 | D5: 0.321 | E5: 0.332
A6: Late 4-7 days | B6: 1748 | C6: 2.1 | D6: 0.677 | E6: 0.141
A7: Late more than 7 days | B7: 2781 | C7: 1.7 | D7: 0.793 | E7: 0.07
A9: Score drop when late (stars) | C9: =C4-SUMPRODUCT(B5:B7,C5:C7)/SUM(B5:B7) -> 2.0189484
A10: Late orders as % of reviewed orders | C10: =SUM(B5:B7)/SUM(B4:B7) -> 0.066590833

Sheet Review_Scores
A1: Review score counts, latest review per order, all orders - from the reviews table
A3: Score | B3: Orders
A4: 1 | B4: 11363
A5: 2 | B5: 3131
A6: 3 | B6: 8133
A7: 4 | B7: 19038
A8: 5 | B8: 57008
A10: Total | B10: =SUM(B4:B8) -> 98673
A11: Average | B11: =SUMPRODUCT(A4:A8,B4:B8)/B10 -> 4.0863863

Sheet Notes
A1: DEFINITIONS AND ASSUMPTIONS
A2: Revenue = sum of item prices (freight excluded) on orders that are not canceled or unavailable. Amounts are in Brazilian reais (R$) per the dataset description; the CSV files themselves carry no currency label.
A3: Orders = distinct orders with at least one item, same status filter as revenue.
A4: Average order value = revenue / orders (item price only). Q7 in the SQL file uses total payments incl. freight, so its numbers are higher.
A5: Delivered = order status "delivered" with a customer delivery date. On-time % = 1 - late orders / delivered orders.
A6: Late = delivery date is on a later calendar day than the estimated delivery date.
A7: Average review score = latest review per order, all 98,673 reviewed orders.
A8: Blue numbers are values taken from the SQL query results (olist_analysis.sql); black numbers are Excel formulas.
A9: Source: Olist Brazilian E-Commerce public dataset (orders from Sep-2016 to Oct-2018).
